deadbeats.py
deadbeats-0.4.0.dist-info/entry_points.txt
deadbeats-0.4.0.dist-info/LICENSE
deadbeats-0.4.0.dist-info/WHEEL
deadbeats-0.4.0.dist-info/METADATA
deadbeats-0.4.0.dist-info/RECORD
