Metadata-Version: 2.1
Name: deadbeats
Version: 0.4.0
Summary: 
Home-page: https://github.com/hpprc/deadbeats
Author: hppRC
Author-email: hpp.ricecake@gmail.com
Requires-Python: >=3.6,<4.0
Classifier: Programming Language :: Python :: 3
Classifier: Programming Language :: Python :: 3.6
Classifier: Programming Language :: Python :: 3.7
Classifier: Programming Language :: Python :: 3.8
Requires-Dist: datetime (>=4.3,<5.0)
Requires-Dist: python-dotenv (>=0.15.0,<0.16.0)
Requires-Dist: requests (>=2.24.0,<3.0.0)
Project-URL: Repository, https://github.com/hpprc/deadbeats
